reflex_roll_hook.pth
reflex_roll/__init__.py
reflex_roll/ezgif-7-4353d96d35.gif
reflex_roll-4.1.2024.dist-info/LICENSE
reflex_roll-4.1.2024.dist-info/METADATA
reflex_roll-4.1.2024.dist-info/WHEEL
reflex_roll-4.1.2024.dist-info/top_level.txt
reflex_roll-4.1.2024.dist-info/RECORD
