Metadata-Version: 2.1
Name: reflex_roll
Version: 4.1.2024
Summary: A more fun connection down indicator your App users will love.
Author-email: Masen Furer <m_github@0x26.net>
License: Apache License
Project-URL: Home, https://github.com/masenf/reflex-roll
Classifier: License :: OSI Approved :: Apache Software License
License-File: LICENSE
